BrawlPlex/__init__.py
BrawlPlex/brawlers.py
BrawlPlex/clubs.py
BrawlPlex/errors.py
BrawlPlex/events.py
BrawlPlex/player.py
BrawlPlex/rankings.py
BrawlPlex-24.7.0.dist-info/LICENSE
BrawlPlex-24.7.0.dist-info/METADATA
BrawlPlex-24.7.0.dist-info/WHEEL
BrawlPlex-24.7.0.dist-info/top_level.txt
BrawlPlex-24.7.0.dist-info/RECORD
